kimwonjoon_lotto/__init__.py
kimwonjoon_lotto/draw.py
kimwonjoon_lotto-0.2.0.dist-info/METADATA
kimwonjoon_lotto-0.2.0.dist-info/WHEEL
kimwonjoon_lotto-0.2.0.dist-info/top_level.txt
kimwonjoon_lotto-0.2.0.dist-info/RECORD
